aresti/__init__.py
aresti/json.py
aresti/py.typed
aresti/rest.py
aresti/sanoma.py
aresti/sivutus.py
aresti/tunnistautuminen.py
aresti/tyokalut.py
aresti/xml.py
aresti/yhteys.py
aresti/rajapinta/__init__.py
aresti/rajapinta/hahmo.py
aresti/rajapinta/tyokalut.py
python_aresti-0.9.15.dist-info/METADATA
python_aresti-0.9.15.dist-info/WHEEL
python_aresti-0.9.15.dist-info/historia.json
python_aresti-0.9.15.dist-info/top_level.txt
python_aresti-0.9.15.dist-info/RECORD
