Metadata-Version: 2.4
Name: python-aresti
Version: 0.9.15
Summary: Asynkroninen REST-rajapintayhteystoteutus
Author-email: Antti Hautaniemi <antti.hautaniemi@pispalanit.fi>
License: MIT
Project-URL: Repository, https://github.com/an7oine/python-aresti.git
Requires-Python: >=3.11
Requires-Dist: aiohttp
Provides-Extra: oauth2
Requires-Dist: pyjwt; extra == "oauth2"
Provides-Extra: xml
Requires-Dist: lxml; extra == "xml"
